nihongo/__init__.py
nihongo/__main__.py
nihongo/core.py
nihongo/transpiler.py
nihongo-0.1.0.dist-info/METADATA
nihongo-0.1.0.dist-info/WHEEL
nihongo-0.1.0.dist-info/top_level.txt
nihongo-0.1.0.dist-info/RECORD
