Metadata-Version: 2.4
Name: nihongo
Version: 0.1.0
Summary: 日本語でコードを書けるミニPythonフレームワーク (Flask風 + トランスパイラ)
Author: くろねこみあ
License: MIT
Requires-Python: >=3.8
